slack_handler/__init__.py
slack_handler/__main__.py
slack_handler/ewf.py
slack_handler/slack.py
slack_handler/utils.py
slack_handler-0.2.11.dist-info/LICENSE
slack_handler-0.2.11.dist-info/METADATA
slack_handler-0.2.11.dist-info/WHEEL
slack_handler-0.2.11.dist-info/entry_points.txt
slack_handler-0.2.11.dist-info/top_level.txt
slack_handler-0.2.11.dist-info/RECORD
