Metadata-Version: 2.1
Name: slack-handler
Version: 0.2.11
Summary: Python tool to extract File slacks from disk images.
Home-page: https://github.com/Sim4n6/Slack_handler
Author: ALJI Mohamed
Author-email: sim4n6@gmail.com
License: GNU General Public License v2.0
Platform: UNKNOWN
License-File: LICENSE
Requires-Dist: pytsk3
Requires-Dist: libewf-python
